snippetlib_jl/.DS_Store
snippetlib_jl/__init__.py
snippetlib_jl/_version.py
snippetlib_jl/handlers.py
snippetlib_jl/loader.py
snippetlib_jl/paste_snippet.py
snippetlib_jl/upload_snippet.py
snippetlib_jl/labextension/snippetlib_jl-0.3.2.tgz
snippetlib_jl/menu/.DS_Store
snippetlib_jl/menu/KD-Snippets/LICENSE
snippetlib_jl/menu/KD-Snippets/README.md
snippetlib_jl/menu/KD-Snippets/Data/Documentation Pandas
snippetlib_jl/menu/KD-Snippets/Data/Read/Read csv.py
snippetlib_jl/menu/KD-Snippets/Data/Read/Read pickle.py
snippetlib_jl/menu/KD-Snippets/Data/Read/Example Data/California housing.py
snippetlib_jl/menu/KD-Snippets/Data/Read/Example Data/Diabetes.py
snippetlib_jl/menu/KD-Snippets/Data/Read/Example Data/Double pendulum.py
snippetlib_jl/menu/KD-Snippets/Data/Read/Example Data/Earthquakes.py
snippetlib_jl/menu/KD-Snippets/Data/Read/Example Data/Iris.py
snippetlib_jl/menu/KD-Snippets/Data/Read/Example Data/Stock data.py
snippetlib_jl/menu/KD-Snippets/Data/Transform/Apply function to attribute.py
snippetlib_jl/menu/KD-Snippets/Data/Transform/Merge on same key.py
snippetlib_jl/menu/KD-Snippets/Data/Transform/Scale and Normalize.py
snippetlib_jl/menu/KD-Snippets/Data/Transform/Select only numeric attributes.py
snippetlib_jl/menu/KD-Snippets/Data/Transform/Set timestamp as index.py
snippetlib_jl/menu/KD-Snippets/Data/Transform/Split into binary attributes.py
snippetlib_jl/menu/KD-Snippets/Data/Write/Write pickle.py
snippetlib_jl/menu/KD-Snippets/Data/Write/Write to csv.py
snippetlib_jl/menu/KD-Snippets/Modelling/Documentation Scikit Learn
snippetlib_jl/menu/KD-Snippets/Modelling/Classification/Decision Tree.py
snippetlib_jl/menu/KD-Snippets/Modelling/Classification/Documentation
snippetlib_jl/menu/KD-Snippets/Modelling/Classification/Gradient Boosting.py
snippetlib_jl/menu/KD-Snippets/Modelling/Classification/KNN-CLassifier.py
snippetlib_jl/menu/KD-Snippets/Modelling/Classification/Logistic Regression.py
snippetlib_jl/menu/KD-Snippets/Modelling/Classification/SVM.py
snippetlib_jl-1.7.2.dist-info/LICENSE
snippetlib_jl-1.7.2.dist-info/METADATA
snippetlib_jl-1.7.2.dist-info/WHEEL
snippetlib_jl-1.7.2.dist-info/top_level.txt
snippetlib_jl-1.7.2.dist-info/RECORD
